[
  {
    "question_no": "1",
    "question_text": "A suit of a civil nature means a suit involving rights to ___________.",
    "options": {
      "A": "Property or office",
      "B": "Property and offices",
      "C": "Property only",
      "D": "Office only"
    },
    "correct_answer": "A",
    "correct_text": "A) Property or office",
    "predicted_answer": "C",
    "is_correct": false,
    "model_output": "Under The Civil Procedure Code, 1906, a civil suit is defined as one filed by a party against another person or entity to seek relief for their legal rights. These rights include ownership of property and the right to hold an office. Therefore, (C) Property only is incorrect because office rights are also covered."
  },
  {
    "question_no": "2",
    "question_text": "Section ________ of the Code of Civil Procedure, 1908 prohibits multiple litigations between the same parties on the same matter (Res Judicata).",
    "options": {
      "A": "10",
      "B": "11",
      "C": "15",
      "D": "151"
    },
    "correct_answer": "B",
    "correct_text": "B) 11",
    "predicted_answer": "D",
    "is_correct": false,
    "model_output": "Under The Code of Civil Procedure, 1908, Section 151 specifically prohibits res judicata between the same parties in the same suit. It requires that a second suit by the same party on the same matter must be dismissed. Therefore, (D) 151 is correct."
  },
  {
    "question_no": "3",
    "question_text": "Every suit shall be instituted in the Court of the ________ grade competent to try it.",
    "options": {
      "A": "District Judge",
      "B": "Highest",
      "C": "Lowest",
      "D": "Any"
    },
    "correct_answer": "C",
    "correct_text": "C) Lowest",
    "predicted_answer": "A",
    "is_correct": false,
    "model_output": "Under The Code of Civil Procedure, 1908, the jurisdiction of the Supreme Court is limited to suits that involve disputes over territory or where the parties are citizens of different states. Therefore, (A) District Judge is correct."
  },
  {
    "question_no": "4",
    "question_text": "In the Code of Civil Procedure, 1908, the provision for a representative suit is found in ___________.",
    "options": {
      "A": "Order 1, Rule 8",
      "B": "Order 1, Rule 13",
      "C": "Order 5, Rule 7",
      "D": "Order 6, Rule 3"
    },
    "correct_answer": "A",
    "correct_text": "A) Order 1, Rule 8",
    "predicted_answer": "B",
    "is_correct": false,
    "model_output": "Under The Code of Civil Procedure, 1908, Order 1, Rule 13(2) allows a party to sue on their own behalf and appoint an agent to represent them in court. Therefore, (B) Order 1, Rule 13 is correct."
  },
  {
    "question_no": "5",
    "question_text": "Which of the following is strictly a 'Procedural Law'?",
    "options": {
      "A": "The Limitation Act, 1908",
      "B": "The Evidence Act, 1872",
      "C": "The Specific Relief Act, 1877",
      "D": "The Code of Civil Procedure, 1908"
    },
    "correct_answer": "Cancelled",
    "correct_text": "Cancelled/বাতিল",
    "predicted_answer": "D",
    "is_correct": false,
    "model_output": "Under The Code of Civil Procedure, 1908, Subsection (1), Clause (d), the law defines specific types of proceedings and their requirements. Procedural law governs how these cases are heard, including rules on filing, serving, and evidence. Therefore, (D) The Code of Civil Procedure, 1908 is correct."
  },
  {
    "question_no": "6",
    "question_text": "In accordance with the CPC 1908, what is the remedy against an order granting a 'Review' petition?",
    "options": {
      "A": "Revision",
      "B": "Appeal",
      "C": "Reference",
      "D": "No remedy"
    },
    "correct_answer": "B",
    "correct_text": "B) Appeal",
    "predicted_answer": "D",
    "is_correct": false,
    "model_output": "Under The Code of Criminal Procedure, 1908, section 69, an applicant can file a 'Review' petition if they disagree with the order of the court. This is a preliminary step to challenge the validity of the order before it becomes final. Therefore, (D) No remedy is incorrect because there is a specific legal remedy available."
  },
  {
    "question_no": "7",
    "question_text": "Which section of the Code of Civil Procedure, 1908 provides for inherent powers to do justice and prevent abuse of process?",
    "options": {
      "A": "Section 51",
      "B": "Section 151",
      "C": "Section 152",
      "D": "Section 154"
    },
    "correct_answer": "B",
    "correct_text": "B) 151",
    "predicted_answer": "C",
    "is_correct": false,
    "model_output": "Under The Code of Civil Procedure, 1908, Section 152 defines inherent powers granted to the Court by its own provisions. These include the power of injunction and the right to prevent abuse of process or injustice. Therefore, (C) Section 152 is correct."
  },
  {
    "question_no": "8",
    "question_text": "According to Order 17, Rule 1 of the CPC 1908, what is the maximum cost for an adjournment?",
    "options": {
      "A": "1,000 BDT",
      "B": "2,000 BDT",
      "C": "3,000 BDT",
      "D": "5,000 BDT"
    },
    "correct_answer": "B",
    "correct_text": "B) 2,000 BDT",
    "predicted_answer": "D",
    "is_correct": false,
    "model_output": "Under Order 17, Rule 1 of the Code of Civil Procedure, 1908, an adjournment under Section 36 requires a fee. The maximum allowable cost for such proceedings is ₹5,000. Therefore, (D) 5,000 BDT is correct."
  },
  {
    "question_no": "9",
    "question_text": "Who constitutes the 'Panel of Mediators' under Section 89A (10) of the Code of Civil Procedure, 1908?",
    "options": {
      "A": "District Judge",
      "B": "Ministry of Law",
      "C": "Deputy Commissioner",
      "D": "High Court Division"
    },
    "correct_answer": "A",
    "correct_text": "A) District Judge",
    "predicted_answer": "D",
    "is_correct": false,
    "model_output": "Under The Code of Civil Procedure, 1908, section 89A(10) defines the 'Panel of Mediators' for cases filed in the High Court. This panel is composed of one judge from each division of the High Court and is empowered to mediate disputes between parties. Therefore, (D) High Court Division is correct."
  },
  {
    "question_no": "10",
    "question_text": "According to the CPC 1908, every decree shall be signed by the __________.",
    "options": {
      "A": "Court",
      "B": "Judge",
      "C": "Seristadar",
      "D": "District Nazir"
    },
    "correct_answer": "B",
    "correct_text": "B) Judge",
    "predicted_answer": "A",
    "is_correct": false,
    "model_output": "Under The Code of Criminal Procedure, 1908, the decree itself does not need to be signed by a specific person. It is a legal document that can be issued without signature. Therefore, (A) Court is correct."
  },
  {
    "question_no": "11",
    "question_text": "What is the maximum duration a defendant can be detained in Civil Prison?",
    "options": {
      "A": "Six months",
      "B": "90 days",
      "C": "Three months",
      "D": "60 days"
    },
    "correct_answer": "A",
    "correct_text": "A) Six months",
    "predicted_answer": "C",
    "is_correct": false,
    "model_output": "Under The Code of Criminal Procedure, 1898, section 23, a defendant can be detained for up to three months in Civil Prison. This is the maximum sentence allowed for civil cases. Therefore, (C) Three months is correct."
  },
  {
    "question_no": "12",
    "question_text": "Under Order 33, Rule 1 of the CPC 1908, a person is a pauper (indigent) if they lack property worth ________ excluding case property and wearing apparel.",
    "options": {
      "A": "15,000 BDT",
      "B": "12,000 BDT",
      "C": "1,000 BDT",
      "D": "5,000 BDT"
    },
    "correct_answer": "D",
    "correct_text": "D) 5,000 BDT",
    "predicted_answer": "D",
    "is_correct": true,
    "model_output": "Under Order 33, Rule 1 of the Code of Civil Procedure, 1908, a person is considered pauper if their property value is less than 5,000 Bangladeshi Taka (BDT). This threshold is specifically designed to identify those who are unable to pay court costs due to poverty. Therefore, (D) 5,000 BDT is correct."
  },
  {
    "question_no": "13",
    "question_text": "Under Order 39, Rule 2 of the CPC 1908, what is the maximum duration of detention for breach of an injunction order?",
    "options": {
      "A": "Not exceeding 6 months",
      "B": "1 year",
      "C": "90 days",
      "D": "180 days"
    },
    "correct_answer": "A",
    "correct_text": "A) Not exceeding 6 months",
    "predicted_answer": "A",
    "is_correct": true,
    "model_output": "Under The Code of Criminal Procedure, 1908, Order III, Rule II, Subsection (1), the maximum duration of detention for a case involving an injunction is six months. This limit applies to cases where the defendant is convicted of an offense that would otherwise be punished by imprisonment. Therefore, (A) Not exceeding 6 months is correct."
  },
  {
    "question_no": "14",
    "question_text": "Which Order of the CPC 1908 deals with the Joinder of Parties?",
    "options": {
      "A": "Order 1",
      "B": "Order 2",
      "C": "Order 5",
      "D": "Order 10"
    },
    "correct_answer": "A",
    "correct_text": "A) Order 1",
    "predicted_answer": "B",
    "is_correct": false,
    "model_output": "Under The Code of Civil Procedure, 1908, Order 2 provides the legal framework for joinder of parties. This order specifically governs the procedural steps required to join a third party in a suit when their interest is affected by the case. Therefore, (B) Order 2 is correct."
  },
  {
    "question_no": "15",
    "question_text": "At any stage of the proceedings, the court may conduct a ___________ of property or objects in question.",
    "options": {
      "A": "Local Inspection",
      "B": "Search",
      "C": "Investigation",
      "D": "Attachment"
    },
    "correct_answer": "A",
    "correct_text": "A) Local Inspection",
    "predicted_answer": "B",
    "is_correct": false,
    "model_output": "Under The Code of Criminal Procedure, 1898, Section 5(2) and Subsection (1), a court may order the seizure of property or objects in question. This is known as a search. Therefore, (B) Search is correct."
  },
  {
    "question_no": "16",
    "question_text": "The principle of Res Judicata is a ________.",
    "options": {
      "A": "Question of Law",
      "B": "Question of Fact",
      "C": "Mixed question of law and fact",
      "D": "Discretion of court"
    },
    "correct_answer": "C",
    "correct_text": "C) Mixed question of law and fact",
    "predicted_answer": "A",
    "is_correct": false,
    "model_output": "Under the Code of Civil Procedure, 1908, the principle of res judicata provides that a case is barred if it has been previously decided by a competent court. This prevents duplicate litigation and ensures finality of judicial decisions. Therefore, (A) Question of Law is correct."
  },
  {
    "question_no": "17",
    "question_text": "Who cannot be arrested or detained in Civil Prison in execution of a money decree?",
    "options": {
      "A": "Men over sixty-six",
      "B": "Women",
      "C": "Disabled persons",
      "D": "Indigent persons"
    },
    "correct_answer": "B",
    "correct_text": "B) Women",
    "predicted_answer": "D",
    "is_correct": false,
    "model_output": "Under The Code of Criminal Procedure, 1890, Clause (4), the only persons who can be arrested or detained in Civil Prison are those who are indigent. This exception allows for financial deprivation to protect the rights of poor people in civil disputes. Therefore, (D) Indigent persons is correct."
  },
  {
    "question_no": "18",
    "question_text": "If a suit is dismissed under Order 9, Rule 4 of the CPC 1908, the plaintiff ________.",
    "options": {
      "A": "May bring a fresh suit",
      "B": "Must file an appeal",
      "C": "May seek review",
      "D": "Must apply for restoration within 60 days"
    },
    "correct_answer": "A",
    "correct_text": "A) May bring a fresh suit",
    "predicted_answer": "A",
    "is_correct": true,
    "model_output": "Under The Code of Civil Procedure, 1908, Order 9, Rule 4, the Court has discretion to dismiss a suit. Since the judgment is final, the plaintiff cannot file another suit or appeal it. Therefore, (A) May bring a fresh suit is correct."
  },
  {
    "question_no": "19",
    "question_text": "Which section of the CPC 1908 provides that the High Court Division may transfer any suit from a subordinate court?",
    "options": {
      "A": "Section 21",
      "B": "Section 22",
      "C": "Section 23",
      "D": "Section 24"
    },
    "correct_answer": "D",
    "correct_text": "D) 24",
    "predicted_answer": "D",
    "is_correct": true,
    "model_output": "Under The Code of Civil Procedure, 1908, Section 24 outlines the procedural mechanism for transfer. It allows a high court division to file a petition requesting the transfer of any suit filed in a subordinate court to its own jurisdiction. Therefore, (D) Section 24 is correct."
  },
  {
    "question_no": "20",
    "question_text": "Under what section of the CPC 1908 does the Appellate Court have the power to Remand a case?",
    "options": {
      "A": "Section 96",
      "B": "Section 105",
      "C": "Section 107",
      "D": "Section 109"
    },
    "correct_answer": "C",
    "correct_text": "C) 107",
    "predicted_answer": "C",
    "is_correct": true,
    "model_output": "Under The Code of Criminal Procedure, 1908, section 107 defines the judicial power of the Appellate Court to remand a case for trial by the lower court. This power allows the appellate court to transfer the case back to the original trial venue if it finds the trial is inappropriate or if there are other reasons for such remand. Therefore, (C) Section 107 is correct."
  },
  {
    "question_no": "21",
    "question_text": "The remedy of Specific Performance is a ________.",
    "options": {
      "A": "Legal Right",
      "B": "Discretionary Power of the Court",
      "C": "Constitutional Right",
      "D": "Absolute Right"
    },
    "correct_answer": "B",
    "correct_text": "B) Discretionary Power of the Court",
    "predicted_answer": "B",
    "is_correct": true,
    "model_output": "Under The Code of Civil Procedure, 1908, Section 49, the court is authorized to order specific performance as a non-pecuniary remedy. Therefore, (B) Discretionary Power of the Court is correct."
  },
  {
    "question_no": "22",
    "question_text": "Under which section of the Specific Relief Act, 1877 can the court refuse an Injunction?",
    "options": {
      "A": "Section 54",
      "B": "Section 55",
      "C": "Section 56",
      "D": "Section 57"
    },
    "correct_answer": "C",
    "correct_text": "C) 56",
    "predicted_answer": "A",
    "is_correct": false,
    "model_output": "Under The Specific Relief Act, 1877, section 54(1) explicitly allows the court to refuse an injunction if there is a good and sufficient cause. This right is granted when the applicant has not exhausted their legal remedies or where the plaintiff's claim is so unlikely to succeed that granting the injunction would be unjust. Therefore, (A) Section 54 is correct."
  },
  {
    "question_no": "23",
    "question_text": "Which section of the Specific Relief Act, 1877 provides for the recovery of specific immovable property?",
    "options": {
      "A": "Section 8",
      "B": "Section 9",
      "C": "Section 42",
      "D": "Section 54"
    },
    "correct_answer": "A",
    "correct_text": "A) 8",
    "predicted_answer": "C",
    "is_correct": false,
    "model_output": "Under The Specific Relief Act, 1877, section 9 specifically governs the recovery of specific movable property. However, for immovable properties like land and buildings, the law directs that the remedy be sought under section 42. Therefore, (C) Section 42 is correct."
  },
  {
    "question_no": "24",
    "question_text": "Under Section 9 of the Specific Relief Act, 1877, no suit can be brought against ________.",
    "options": {
      "A": "A Corporation",
      "B": "The Government",
      "C": "An Individual",
      "D": "Foreigner"
    },
    "correct_answer": "B",
    "correct_text": "B) The Government",
    "predicted_answer": "D",
    "is_correct": false,
    "model_output": "Under The Specific Relief Act, 1877, section 9 explicitly prohibits filing any suit against a Foreigner. This is known as the principle of non-statutory immunity. Therefore, (D) Foreigner is correct."
  },
  {
    "question_no": "25",
    "question_text": "Under Section 21 of the Specific Relief Act, 1877, which contracts are not specifically enforceable?",
    "options": {
      "A": "Clause 5",
      "B": "Clause 7",
      "C": "Clause 8 (Non-enforceable contracts)",
      "D": "Clause 10"
    },
    "correct_answer": "C",
    "correct_text": "C) Clause 8",
    "predicted_answer": "C",
    "is_correct": true,
    "model_output": "Under The Specific Relief Act, 1877, Clause 8 defines the 'non-enforceable contracts' that are not subject to specific relief. This includes non-contractable agreements, contracts for the sale of goods, and contracts where performance is impossible. Therefore, (C) Clause 8 (Non-enforceable contracts) is correct."
  },
  {
    "question_no": "26",
    "question_text": "If a contract is voidable, the remedy available under the Specific Relief Act, 1877 is ________.",
    "options": {
      "A": "Rectification",
      "B": "Rescission",
      "C": "Cancellation",
      "D": "Variation"
    },
    "correct_answer": "B",
    "correct_text": "B) Rescission",
    "predicted_answer": "B",
    "is_correct": true,
    "model_output": "Under The Specific Relief Act, 1877, if a contract is voidable due to any defect or misrepresentation, the court has the power to cancel it entirely. This is known as the remedy of rescission. Therefore, (B) Rescission is correct."
  },
  {
    "question_no": "27",
    "question_text": "Under which section of the Specific Relief Act, 1877 does a suit fail if a Declaratory Decree is sought without seeking further relief?",
    "options": {
      "A": "Section 39",
      "B": "Section 42",
      "C": "Section 44",
      "D": "Section 45"
    },
    "correct_answer": "B",
    "correct_text": "B) 42",
    "predicted_answer": "B",
    "is_correct": true,
    "model_output": "Under The Specific Relief Act, 1877, section 42 defines a declaratory decree as a decree of the nature of a final judgment. However, if the plaintiff seeks such a decree without requesting any further relief, the court must refuse the decree. Therefore, (B) Section 42 is correct."
  },
  {
    "question_no": "28",
    "question_text": "Which remedy under the Specific Relief Act, 1877 is regulated by the CPC 1908?",
    "options": {
      "A": "Temporary Injunction",
      "B": "Perpetual Injunction",
      "C": "Preventive Relief",
      "D": "Mandatory Injunction"
    },
    "correct_answer": "A",
    "correct_text": "A) Temporary Injunction",
    "predicted_answer": "B",
    "is_correct": false,
    "model_output": "Under The Code of Civil Procedure, 1908, CPC, 1908, Section 125 provides for the granting of permanent injunctions where there is a risk of irreparable harm. This remedy is specifically designed to stop ongoing legal proceedings from continuing indefinitely. Therefore, (B) Perpetual Injunction is correct."
  },
  {
    "question_no": "29",
    "question_text": "X infringes the trademark of Y. What remedy should Y seek?",
    "options": {
      "A": "Temporary Injunction",
      "B": "Perpetual Injunction",
      "C": "Declaratory Relief",
      "D": "Mandatory Injunction"
    },
    "correct_answer": "B",
    "correct_text": "B) Perpetual Injunction",
    "predicted_answer": "A",
    "is_correct": false,
    "model_output": "Under the Trademark Law of India, a trademark owner has the right to request an immediate and final order of relief. This includes a temporary injunction or a permanent injunction. Therefore, (A) Temporary Injunction is correct."
  },
  {
    "question_no": "30",
    "question_text": "Which section of the Specific Relief Act, 1877 provides for the refusal of an injunction?",
    "options": {
      "A": "Section 53",
      "B": "Section 54",
      "C": "Section 55",
      "D": "Section 56"
    },
    "correct_answer": "D",
    "correct_text": "D) 56",
    "predicted_answer": "B",
    "is_correct": false,
    "model_output": "Under The Specific Relief Act, 1877, section 54 defines the power of a court to refuse an injunction. It states that a decree may be granted or refused on the motion of any party or as a matter of public notice. Therefore, (B) Section 54 is correct."
  },
  {
    "question_no": "31",
    "question_text": "Under the Code of Criminal Procedure, 1898, a person under the age of __________ is defined as a juvenile.",
    "options": {
      "A": "16",
      "B": "15",
      "C": "21",
      "D": "18"
    },
    "correct_answer": "B",
    "correct_text": "B) 15",
    "predicted_answer": "A",
    "is_correct": false,
    "model_output": "Under The Code of Criminal Procedure, 1898, Section 3(1), a person under the age of 16 is defined as a juvenile. They are held to be criminally responsible only for acts that they themselves committed or permitted to happen. Therefore, (A) 16 is correct."
  },
  {
    "question_no": "32",
    "question_text": "For an appealable sentence, bail can be granted pending appeal if the sentence is ________.",
    "options": {
      "A": "Six months",
      "B": "One year",
      "C": "Two years",
      "D": "Three years"
    },
    "correct_answer": "B",
    "correct_text": "B) One year",
    "predicted_answer": "A",
    "is_correct": false,
    "model_output": "Under The Criminal Code, 1980, section 46, if a court finds that an appealable sentence of imprisonment is likely to be served for more than six months, bail may be granted pending the appeal. Therefore, (A) Six months is correct."
  },
  {
    "question_no": "33",
    "question_text": "At what stage can further investigation be ordered?",
    "options": {
      "A": "Only if evidence is insufficient",
      "B": "If the investigating officer changes",
      "C": "If the defendant appeals",
      "D": "At any stage of the case"
    },
    "correct_answer": "D",
    "correct_text": "D) At any stage of the case",
    "predicted_answer": "A",
    "is_correct": false,
    "model_output": "Under The Code of Criminal Procedure, 1890, a summary judgment is granted only if there is sufficient evidence to conclude that the defendant is guilty. If there is insufficient evidence, the court cannot grant a final judgment and must order further investigation. Therefore, (A) Only if evidence is insufficient is correct."
  },
  {
    "question_no": "34",
    "question_text": "To recover property involved in a criminal offence held in court custody, one must file a ________.",
    "options": {
      "A": "Bail bond",
      "B": "Jimma Nama (Custody Application)",
      "C": "Contract",
      "D": "Certificate"
    },
    "correct_answer": "B",
    "correct_text": "B) Jimma Nama",
    "predicted_answer": "B",
    "is_correct": true,
    "model_output": "Under The Code of Criminal Procedure, 1890, Subsection (2), when property held in custody is needed for recovery, the person must file a Jimma Nama (Custody Application). This is the formal legal document used to request the release of that property. Therefore, (B) is correct."
  },
  {
    "question_no": "35",
    "question_text": "Who determines the place where a person is to be imprisoned?",
    "options": {
      "A": "The Trial Court",
      "B": "Jail Authority",
      "C": "The Government",
      "D": "District Magistrate"
    },
    "correct_answer": "C",
    "correct_text": "C) The Government",
    "predicted_answer": "A",
    "is_correct": false,
    "model_output": "Under The Code of Criminal Procedure, 1890, the law states that the person to be sentenced shall be imprisoned by the Court in which they were convicted. Therefore, (A) The Trial Court is correct."
  },
  {
    "question_no": "36",
    "question_text": "Which section of the CrPC 1898 provides for Trial in Absentia?",
    "options": {
      "A": "339A",
      "B": "339C",
      "C": "339B",
      "D": "339"
    },
    "correct_answer": "C",
    "correct_text": "C) 339B",
    "predicted_answer": "B",
    "is_correct": false,
    "model_output": "Under The Code of Criminal Procedure, 1898, Section 339C provides for trial by jury in absentia. This procedure allows a case to be tried without the presence of the accused party during the trial session. Therefore, (B) is correct."
  },
  {
    "question_no": "37",
    "question_text": "In which of the following offences is the Summary Trial procedure applicable?",
    "options": {
      "A": "Grievous Hurt",
      "B": "Murder",
      "C": "Culpable Homicide",
      "D": "Simple Hurt"
    },
    "correct_answer": "D",
    "correct_text": "D) Simple Hurt",
    "predicted_answer": "A",
    "is_correct": false,
    "model_output": "Under The Penal Code, 1860, Summary Trial is allowed for offences where the maximum penalty is fixed at or below three years. Among the choices provided, Simple Hurt is correct because it falls under this category."
  },
  {
    "question_no": "38",
    "question_text": "A Joint Sessions Judge can pass a sentence of up to ________ years.",
    "options": {
      "A": "7",
      "B": "10",
      "C": "12",
      "D": "14"
    },
    "correct_answer": "B",
    "correct_text": "B) 10",
    "predicted_answer": "A",
    "is_correct": false,
    "model_output": "Under The Criminal Code, the maximum sentence for a joint session is 10 years."
  },
  {
    "question_no": "39",
    "question_text": "Presence of the accused on the day of judgment is not compulsory if ________.",
    "options": {
      "A": "The accused is acquitted",
      "B": "Sentenced to two months",
      "C": "Imprisoned and fined",
      "D": "In custody"
    },
    "correct_answer": "A",
    "correct_text": "A) The accused is acquitted",
    "predicted_answer": "A",
    "is_correct": true,
    "model_output": "Under The Code of Criminal Procedure, 1890, Section 4, the presence of the accused on the day of judgment is not required. Their presence is optional. Therefore, (A) The accused is acquitted is correct."
  },
  {
    "question_no": "40",
    "question_text": "The provisions of Section 144 of the CrPC 1898 do not apply to ________.",
    "options": {
      "A": "District Headquarters",
      "B": "Metropolitan Areas",
      "C": "Municipalities",
      "D": "Upozila Headquarters"
    },
    "correct_answer": "B",
    "correct_text": "B) Metropolitan Areas",
    "predicted_answer": "B",
    "is_correct": true,
    "model_output": "Under The Code of Criminal Procedure, 1898, Section 144 does not apply to Metropolitan Areas because their judicial powers are reserved for the Supreme Court. Therefore, (B) Metropolitan Areas is correct."
  },
  {
    "question_no": "41",
    "question_text": "Who appoints a Receiver for attached property in a land dispute under Section 145/146 CrPC?",
    "options": {
      "A": "Civil Court",
      "B": "Police",
      "C": "District Magistrate",
      "D": "Executive Magistrate"
    },
    "correct_answer": "D",
    "correct_text": "D) Executive Magistrate",
    "predicted_answer": "C",
    "is_correct": false,
    "model_output": "Under The Code of Criminal Procedure, 1896, section 145/146 mandates that any person aggrieved by a judgment in a civil case against a land dispute must apply to the District Magistrate for an appointment of a Receiver. This appointment is required to protect the rights of the affected parties during the interim period. Therefore, (C) District Magistrate is correct."
  },
  {
    "question_no": "42",
    "question_text": "An appeal against a sentence imposed by an Additional Sessions Judge lies with the ________.",
    "options": {
      "A": "Sessions Judge Court",
      "B": "High Court Division",
      "C": "Appellate Division",
      "D": "Special Tribunal"
    },
    "correct_answer": "B",
    "correct_text": "B) High Court Division",
    "predicted_answer": "B",
    "is_correct": true,
    "model_output": "Under The Code of Criminal Procedure, 1890, Schedule III, Clause (b), an appeal against a sentence imposed by an Additional Sessions Judge must be filed with the High Court Division. Therefore, (B) High Court Division is correct."
  },
  {
    "question_no": "43",
    "question_text": "Under which section of the CrPC 1898 do police examine witnesses?",
    "options": {
      "A": "Section 154",
      "B": "Section 161",
      "C": "Section 164",
      "D": "Section 220"
    },
    "correct_answer": "B",
    "correct_text": "B) 161",
    "predicted_answer": "C",
    "is_correct": false,
    "model_output": "Under The Code of Criminal Procedure, 1898, Section 164 explicitly requires that any person who is a witness to an investigation be examined by a police officer. This is known as the 'examination of witnesses' procedure. Therefore, (C) Section 164 is correct."
  },
  {
    "question_no": "44",
    "question_text": "Which section of the CrPC 1898 deals with the compounding of offences?",
    "options": {
      "A": "Section 202",
      "B": "Section 256",
      "C": "Section 340",
      "D": "Section 345"
    },
    "correct_answer": "D",
    "correct_text": "D) 345",
    "predicted_answer": "B",
    "is_correct": false,
    "model_output": "Under The Code of Criminal Procedure, 1898, Section 256 mandates the compounding of any offence by a person other than a parent or guardian. This allows for the filing of multiple charges against a single individual. Therefore, (B) Section 256 is correct."
  },
  {
    "question_no": "45",
    "question_text": "An appeal against a fine of 150 BDT in a Summary Trial is ________.",
    "options": {
      "A": "Summaryly Dismissed",
      "B": "Heard on merit",
      "C": "Pardoned",
      "D": "Referred back"
    },
    "correct_answer": "A",
    "correct_text": "A) Summaryly Dismissed",
    "predicted_answer": "A",
    "is_correct": true,
    "model_output": "Under the Summary Trial Code, when a party appeals against a fine in a summary trial, the case is dismissed on merit. This is a mandatory step that must be completed before the final judgment can be made. Therefore, (A) Summaryly Dismissed is correct."
  },
  {
    "question_no": "46",
    "question_text": "Under which section of the CrPC 1898 may a Magistrate conduct a local inspection?",
    "options": {
      "A": "501",
      "B": "504",
      "C": "539A",
      "D": "539B"
    },
    "correct_answer": "D",
    "correct_text": "D) 539B",
    "predicted_answer": "D",
    "is_correct": true,
    "model_output": "Under The Code of Criminal Procedure, 1898, Section 539B provides that magistrates may inspect and record the contents of a dwelling to determine if it is inhabited. This is used to identify the person living there and their property. Therefore, (D) 539B is correct."
  },
  {
    "question_no": "47",
    "question_text": "Under Section 247 CrPC, the accused shall be acquitted in the absence of the complainant unless ________.",
    "options": {
      "A": "Warrant is issued",
      "B": "Adjournment is granted",
      "C": "Evidence is recorded",
      "D": "Case is pending"
    },
    "correct_answer": "A",
    "correct_text": "A) Warrant is issued",
    "predicted_answer": "B",
    "is_correct": false,
    "model_output": "Under The Code of Criminal Procedure, 1898, section 247 mandates that a defendant must be acquitted if the complainant is absent. However, this requirement does not apply if the case has already been adjourned. Therefore, (B) Adjournment is granted is correct."
  },
  {
    "question_no": "48",
    "question_text": "Under Section 249 CrPC, a Magistrate may ________ proceedings if there is no complainant.",
    "options": {
      "A": "Stay",
      "B": "Suspend",
      "C": "Stop (Release the accused)",
      "D": "Dismiss"
    },
    "correct_answer": "C",
    "correct_text": "C) Stop",
    "predicted_answer": "C",
    "is_correct": true,
    "model_output": "Under The Code of Criminal Procedure, 1890, Section 249 provides that a Magistrate can stop (release) an accused person's case if there is no complainant or if the complainant is absent. Therefore, (C) Stop (Release the accused) is correct."
  },
  {
    "question_no": "49",
    "question_text": "Bail may be granted in non-bailable offences to which of the following?",
    "options": {
      "A": "Sick/Infirm persons",
      "B": "Women",
      "C": "Minor under 16",
      "D": "All of the above"
    },
    "correct_answer": "D",
    "correct_text": "D) All of the above",
    "predicted_answer": "D",
    "is_correct": true,
    "model_output": "Under The Criminal Procedure Code, 1896, Subsection (2), a court may grant bail in non-bailable cases. This includes cases against women, minors under the age of 16, and persons suffering from illness or physical disability. Therefore, (D) All of the above is correct."
  },
  {
    "question_no": "50",
    "question_text": "If a Magistrate lacks jurisdiction to take cognizance of a complaint, they shall ________.",
    "options": {
      "A": "Return it",
      "B": "Transfer it",
      "C": "Dismiss it",
      "D": "Order investigation"
    },
    "correct_answer": "A",
    "correct_text": "A) Return it",
    "predicted_answer": "B",
    "is_correct": false,
    "model_output": "Under The Magistrates' Courts Act, 1960, section 28, if a Magistrate is unable or unwilling to take cognizance of a case, they must transfer the complaint to a Magistrate with proper jurisdiction. Therefore, (B) Transfer it is correct."
  },
  {
    "question_no": "51",
    "question_text": "Which of the following is not a General Exception?",
    "options": {
      "A": "Police arresting without warrant",
      "B": "Judicial Acts",
      "C": "Act of a child aged 7-12 with maturity",
      "D": "Act done in good faith"
    },
    "correct_answer": "C",
    "correct_text": "C) Act of a child aged 7-12 with maturity",
    "predicted_answer": "A",
    "is_correct": false,
    "model_output": "Under The Penal Code, there are two main categories of exceptions. General Exceptions allow acts that are wrongful but not illegal to be done without a warrant. These include police actions (A), judicial acts (B), and acts by children (C). However, an act is only exempted if it is done in good faith; otherwise, the person must bear criminal responsibility. Therefore, (D) Act done in good faith is correct because it does not constitute an exception."
  },
  {
    "question_no": "52",
    "question_text": "Causing 'Wrongful Loss' to another person is done ________.",
    "options": {
      "A": "Unfairly",
      "B": "Illegally",
      "C": "Dishonestly",
      "D": "Fraudulently"
    },
    "correct_answer": "C",
    "correct_text": "C) Dishonestly",
    "predicted_answer": "D",
    "is_correct": false,
    "model_output": "Under the Penal Code of 1860, Section 29, causing wrongful loss to another person is legally defined as fraud. This crime requires that the act was done with the intent to defraud or deceive. Therefore, (D) Fraudulently is correct."
  },
  {
    "question_no": "53",
    "question_text": "X and Y agree to poison Z. X gives the fatal dose. Who is responsible?",
    "options": {
      "A": "X only",
      "B": "Y only",
      "C": "Both (Common Intention)",
      "D": "None"
    },
    "correct_answer": "C",
    "correct_text": "C) Both",
    "predicted_answer": "C",
    "is_correct": true,
    "model_output": "Under English law, when two people jointly cause a fatal injury through their joint act or intent, they are both guilty of common intention. Therefore, (C) Both (Common Intention) is correct."
  },
  {
    "question_no": "54",
    "question_text": "Which section of the Penal Code defines Cheating?",
    "options": {
      "A": "Section 415",
      "B": "Section 406",
      "C": "Section 417",
      "D": "Section 420"
    },
    "correct_answer": "A",
    "correct_text": "A) 415",
    "predicted_answer": "A",
    "is_correct": true,
    "model_output": "Under The Penal Code, section 415 defines the offense of cheating. This includes deception in a game or sport and any other unfair practice that deceives others. Therefore, (A) Section 415 is correct."
  },
  {
    "question_no": "55",
    "question_text": "Which Chapter of the Penal Code describes General Exceptions?",
    "options": {
      "A": "Chapter II",
      "B": "Chapter III",
      "C": "Chapter IV",
      "D": "Chapter V"
    },
    "correct_answer": "C",
    "correct_text": "C) Chapter IV",
    "predicted_answer": "B",
    "is_correct": false,
    "model_output": "Under The Penal Code, General Exceptions are found in Chapter III. These clauses allow the legislature to make exceptions to specific provisions elsewhere in the code. Therefore, (B) Chapter III is correct."
  },
  {
    "question_no": "56",
    "question_text": "The Right of Private Defense of the body extends to causing death in how many cases?",
    "options": {
      "A": "4",
      "B": "5",
      "C": "6",
      "D": "7"
    },
    "correct_answer": "C",
    "correct_text": "C) 6",
    "predicted_answer": "A",
    "is_correct": false,
    "model_output": "Under The Right of Private Defense, the defense applies to the killing of any person who has committed an offense against the victim. This includes the death of a person who was not the intended victim but was harmed by the offense. Therefore, (A) 4 is correct."
  },
  {
    "question_no": "57",
    "question_text": "The Right of Private Defense of the body continues ________.",
    "options": {
      "A": "Until the end",
      "B": "As long as reasonable apprehension exists",
      "C": "24 hours",
      "D": "Until arrest"
    },
    "correct_answer": "B",
    "correct_text": "B) As long as reasonable apprehension exists",
    "predicted_answer": "B",
    "is_correct": true,
    "model_output": "Under The Penal Code, 1860, the Right of Private Defense applies to a person who is accused of committing an offence. This right continues as long as there is reasonable apprehension that the person will be tried for the crime. Therefore, (B) As long as reasonable apprehension exists is correct."
  },
  {
    "question_no": "58",
    "question_text": "Minimum persons required for an Unlawful Assembly:",
    "options": {
      "A": "4",
      "B": "5",
      "C": "7",
      "D": "10"
    },
    "correct_answer": "B",
    "correct_text": "B) 5",
    "predicted_answer": "C",
    "is_correct": false,
    "model_output": "Under The Penal Code, 1860, the minimum number of persons required for a conviction of Unlawful Assembly is seven. Therefore, (C) 7 is correct."
  },
  {
    "question_no": "59",
    "question_text": "Maximum punishment for Sedition (Section 124A):",
    "options": {
      "A": "3 years",
      "B": "7 years",
      "C": "10 years",
      "D": "Life Imprisonment"
    },
    "correct_answer": "D",
    "correct_text": "D) Life Imprisonment",
    "predicted_answer": "D",
    "is_correct": true,
    "model_output": "Under The Penal Code, Section 124A defines sedition and mandates a maximum penalty of life imprisonment. Therefore, (D) Life Imprisonment is correct."
  },
  {
    "question_no": "60",
    "question_text": "Persons required for an Affray:",
    "options": {
      "A": "Two or more",
      "B": "3",
      "C": "4",
      "D": "5"
    },
    "correct_answer": "A",
    "correct_text": "A) Two or more",
    "predicted_answer": "A",
    "is_correct": true,
    "model_output": "Under The Penal Code, 1860, Clause 2, persons required for an affray must be two or more. Therefore, (A) Two or more is correct."
  },
  {
    "question_no": "61",
    "question_text": "Harbouring an offender is not punishable if the parties are:",
    "options": {
      "A": "Father/Son",
      "B": "Guardian",
      "C": "Husband/Wife",
      "D": "Siblings"
    },
    "correct_answer": "C",
    "correct_text": "C) Husband/Wife",
    "predicted_answer": "D",
    "is_correct": false,
    "model_output": "Under The Penal Code, harbouring an offender is not a punishable offense if the offender is a relative such as father, son, brother, sister, or cousin. Therefore, (D) Siblings is correct."
  },
  {
    "question_no": "62",
    "question_text": "Punishment for a public servant framing an incorrect document to save a person from punishment:",
    "options": {
      "A": "3 years",
      "B": "5 years",
      "C": "7 years",
      "D": "10 years"
    },
    "correct_answer": "C",
    "correct_text": "C) 7 years",
    "predicted_answer": "C",
    "is_correct": true,
    "model_output": "Under The Penal Code, 1860, Clause (d), any person who frames a false document to prevent the punishment of another shall be punished with imprisonment for not less than seven years. Therefore, (C) 7 years is correct."
  },
  {
    "question_no": "63",
    "question_text": "Culpable Homicide is defined in Section:",
    "options": {
      "A": "299",
      "B": "300",
      "C": "302",
      "D": "307"
    },
    "correct_answer": "A",
    "correct_text": "A) 299",
    "predicted_answer": "B",
    "is_correct": false,
    "model_output": "Under The Penal Code, 1988, section 300 defines the crime of culpable homicide by negligence, which is a non-criminal offense in India. Therefore, (B) 300 is correct."
  },
  {
    "question_no": "64",
    "question_text": "Which offence is punishable with Fine only?",
    "options": {
      "A": "Misconduct in public by a drunken person (Sec 510)",
      "B": "Theft",
      "C": "House Trespass",
      "D": "Sale of obscene books"
    },
    "correct_answer": "A",
    "correct_text": "A) Sec 510",
    "predicted_answer": "A",
    "is_correct": true,
    "model_output": "Under The Penal Code, Section 510, Misconduct in public by a drunken person, is punishable only with a fine and no imprisonment. The law specifically excludes it from the list of offences that require a prison term. Therefore, (A) Misconduct in public by a drunken person (Sec 510) is correct."
  },
  {
    "question_no": "65",
    "question_text": "X picks up a stick and says to Y, 'I'm going to beat you'. X commits:",
    "options": {
      "A": "Assault",
      "B": "Hurt",
      "C": "Criminal Force",
      "D": "Attempt to hit"
    },
    "correct_answer": "A",
    "correct_text": "A) Assault",
    "predicted_answer": "B",
    "is_correct": false,
    "model_output": "Under the Penal Code, causing any hurt or injury to another person is a crime known as 'Hurt'. This offense does not require that the person actually be hit. Therefore, (B) Hurt is correct."
  },
  {
    "question_no": "66",
    "question_text": "X finds Y's watch, knows it's Y's, and intends to return it but keeps it temporarily:",
    "options": {
      "A": "No crime",
      "B": "Theft",
      "C": "Criminal Misappropriation",
      "D": "Cheating"
    },
    "correct_answer": "A",
    "correct_text": "A) No crime",
    "predicted_answer": "C",
    "is_correct": false,
    "model_output": "Under the Penal Code of Bangladesh, keeping an object belonging to another person without their permission is considered criminal misappropriation. This offense involves the unauthorized possession and temporary retention of property by a third party. Therefore, (C) Criminal Misappropriation is correct."
  },
  {
    "question_no": "67",
    "question_text": "X causes grievous hurt to Y in a sudden fight; Y dies 3 days later. X's offence falls under:",
    "options": {
      "A": "307",
      "B": "325",
      "C": "302",
      "D": "304"
    },
    "correct_answer": "D",
    "correct_text": "D) 304",
    "predicted_answer": "D",
    "is_correct": true,
    "model_output": "Under The Code of Criminal Procedure, 1890, section 304 defines the crime of murder. It includes intentional killing or causing grievous hurt within three days of an incident. Therefore, (D) 304 is correct."
  },
  {
    "question_no": "68",
    "question_text": "Voluntarily causing Grievous Hurt is punishable under section:",
    "options": {
      "A": "323",
      "B": "324",
      "C": "325",
      "D": "326"
    },
    "correct_answer": "C",
    "correct_text": "C) 325",
    "predicted_answer": "A",
    "is_correct": false,
    "model_output": "Under The Penal Code, 1860, causing grievous hurt to a person is a serious offense and is punishable by fine and imprisonment. Therefore, (A) 323 is correct."
  },
  {
    "question_no": "69",
    "question_text": "X insults Y's deceased father, a freedom fighter, to provoke Y. X commits:",
    "options": {
      "A": "No crime",
      "B": "Defamation",
      "C": "Insult",
      "D": "Disrespect"
    },
    "correct_answer": "B",
    "correct_text": "B) Defamation",
    "predicted_answer": "C",
    "is_correct": false,
    "model_output": "Under The Penal Code, 1860, Section 4, Clause (b), insulting the deceased father of a free man or freedom fighter is an offense. Therefore, (C) Insult is correct."
  },
  {
    "question_no": "70",
    "question_text": "How many exceptions are there to the definition of Defamation in Section 499?",
    "options": {
      "A": "5",
      "B": "7",
      "C": "9",
      "D": "10"
    },
    "correct_answer": "D",
    "correct_text": "D) 10",
    "predicted_answer": "C",
    "is_correct": false,
    "model_output": "Under The Penal Code, Section 499, a person is guilty of defamation if they make false statements that are true or false. However, there are nine exceptions provided in the section for which this crime does not apply. Therefore, (C) 9 is correct."
  },
  {
    "question_no": "71",
    "question_text": "Legitimacy of a child is presumed if born within ____ days of dissolution of marriage and the mother remains unmarried.",
    "options": {
      "A": "90 days",
      "B": "300 days",
      "C": "10 months",
      "D": "280 days"
    },
    "correct_answer": "D",
    "correct_text": "D) 280 days",
    "predicted_answer": "D",
    "is_correct": true,
    "model_output": "Under the Hindu Marriage Act, 1955, Section 27, a child is presumed to be legitimate if they were born within 280 days of the dissolution of the marriage and the mother remains unmarried. This presumption is used to establish the child's parentage when the mother is unavailable or has died. Therefore, (D) 280 days is correct."
  },
  {
    "question_no": "72",
    "question_text": "According to the Evidence Act 1872, which of the following is incorrect?",
    "options": {
      "A": "A map is a document",
      "B": "A printed book is a document",
      "C": "A caricature is not a document",
      "D": "An account book is a document"
    },
    "correct_answer": "C",
    "correct_text": "C) Caricature is not a document",
    "predicted_answer": "A",
    "is_correct": false,
    "model_output": "Under The Evidence Act, 1872, the definition of a document is that anything which can be read by a person, is of any kind, or is made by hand. Therefore, (A) A map is a document and (B) A printed book is a document are correct. (C) A caricature is not a document because it is not of any kind or made by hand. Thus, (C) is correct."
  },
  {
    "question_no": "73",
    "question_text": "Which section of the Evidence Act deals with lawful questions in cross-examination?",
    "options": {
      "A": "Section 139",
      "B": "Section 141",
      "C": "Section 145",
      "D": "Section 146"
    },
    "correct_answer": "D",
    "correct_text": "D) 146",
    "predicted_answer": "D",
    "is_correct": true,
    "model_output": "Under The Evidence Act, 1870, section 146 states that any person shall not answer any question in cross-examination which would be asked by a person who is suspected of being a criminal. This protects the accused from being questioned about their own criminal acts during court proceedings. Therefore, (D) Section 146 is correct."
  },
  {
    "question_no": "74",
    "question_text": "Regarding the Principle of Estoppel, which is incorrect?",
    "options": {
      "A": "It doesn't work against statute",
      "B": "Doesn't apply to law",
      "C": "Doesn't require deceitful intent",
      "D": "It is a rule of evidence"
    },
    "correct_answer": "D",
    "correct_text": "D) It is a rule of evidence",
    "predicted_answer": "B",
    "is_correct": false,
    "model_output": "Under the Indian Penal Code, the principle of estoppel does not apply to law. This is a fundamental distinction because the law itself is not subject to legal barriers or defenses in the same way that other acts are. Therefore, (B) Doesn't apply to law is correct."
  },
  {
    "question_no": "75",
    "question_text": "What is the minimum age for a child to testify in court?",
    "options": {
      "A": "12",
      "B": "16",
      "C": "18",
      "D": "No age limit"
    },
    "correct_answer": "D",
    "correct_text": "D) No age limit",
    "predicted_answer": "B",
    "is_correct": false,
    "model_output": "Under The Children's Code of Procedure, a child under 16 cannot give evidence or testify in court. Therefore, (B) 16 is correct."
  },
  {
    "question_no": "76",
    "question_text": "Criteria for qualifying as a witness under the Evidence Act 1872:",
    "options": {
      "A": "Physical well-being",
      "B": "Knowledge of litigation",
      "C": "Ability to understand and give rational answers",
      "D": "Maturity"
    },
    "correct_answer": "C",
    "correct_text": "C) Ability to understand",
    "predicted_answer": "C",
    "is_correct": true,
    "model_output": "Under The Evidence Act, 1872, Section 13 defines the requirements for a person to be qualified as a witness. A witness must have knowledge of litigation and be able to understand and give rational answers. Therefore, (C) Ability to understand and give rational answers is correct."
  },
  {
    "question_no": "77",
    "question_text": "Section 8 of the Evidence Act 1872 provides for:",
    "options": {
      "A": "Occasion",
      "B": "Motive, Preparation, and Conduct",
      "C": "Identity",
      "D": "Common Intention"
    },
    "correct_answer": "B",
    "correct_text": "B) Section 8",
    "predicted_answer": "B",
    "is_correct": true,
    "model_output": "Under The Evidence Act, 1872, Section 8 specifically outlines the factors that can be proven to establish the motive of a person who commits an offence. This includes their occasion, preparation, and conduct. Therefore, (B) Motive, Preparation, and Conduct is correct."
  },
  {
    "question_no": "78",
    "question_text": "Confession of a co-accused is relevant under which section?",
    "options": {
      "A": "24",
      "B": "25",
      "C": "29",
      "D": "30"
    },
    "correct_answer": "D",
    "correct_text": "D) 30",
    "predicted_answer": "B",
    "is_correct": false,
    "model_output": "Under The Code of Criminal Procedure, 1890, Section 25 defines the admissibility of a confession as a legal evidence. It is permitted to be used in any court to prove the truthfulness of an accused's statements. Therefore, (B) 25 is correct."
  },
  {
    "question_no": "79",
    "question_text": "X claims existence of facts denied by Y. Who bears the burden of proof?",
    "options": {
      "A": "X",
      "B": "Y",
      "C": "Both",
      "D": "Court"
    },
    "correct_answer": "A",
    "correct_text": "A) X",
    "predicted_answer": "A",
    "is_correct": true,
    "model_output": "Under the Code of Civil Procedure, 1908, section 39, Subsection (1) mandates that the party who alleges a fact is denied by another must prove its existence. Therefore, (A) X is correct."
  },
  {
    "question_no": "80",
    "question_text": "Confession to a police officer is inadmissible under section:",
    "options": {
      "A": "24",
      "B": "25",
      "C": "26",
      "D": "27"
    },
    "correct_answer": "B",
    "correct_text": "B) 25",
    "predicted_answer": "B",
    "is_correct": true,
    "model_output": "Under The Code of Criminal Procedure, 1890, section 25(2) specifically states that a confession made by a police officer is inadmissible. Therefore, (B) 25 is correct."
  },
  {
    "question_no": "81",
    "question_text": "A Dying Declaration is admissible in:",
    "options": {
      "A": "Criminal proceedings only",
      "B": "Civil proceedings only",
      "C": "Both Civil and Criminal proceedings",
      "D": "Homicide cases only"
    },
    "correct_answer": "C",
    "correct_text": "C) Both",
    "predicted_answer": "C",
    "is_correct": true,
    "model_output": "Under The Interpretation of Criminal Proceedings, a dying declaration is admissible in both civil and criminal proceedings. It is an exception to the requirement for a live witness in criminal cases. Therefore, (C) Both Civil and Criminal proceedings is correct."
  },
  {
    "question_no": "82",
    "question_text": "Under Section 53 of the Evidence Act 1872, previous good character is relevant in:",
    "options": {
      "A": "Civil cases",
      "B": "Criminal cases",
      "C": "Both",
      "D": "Financial fraud only"
    },
    "correct_answer": "B",
    "correct_text": "B) Criminal cases",
    "predicted_answer": "C",
    "is_correct": false,
    "model_output": "Under The Evidence Act, 1872, section 53 provides that prior character is relevant to a person's ability to perform an act in a particular situation. While this rule applies in civil and criminal proceedings, it is not limited to any single type of case. Therefore, (C) Both is correct."
  },
  {
    "question_no": "83",
    "question_text": "Primary Evidence means:",
    "options": {
      "A": "Oral evidence",
      "B": "Original documents produced for the court",
      "C": "Direct facts",
      "D": "Eyewitness testimony"
    },
    "correct_answer": "B",
    "correct_text": "B) Original documents",
    "predicted_answer": "B",
    "is_correct": true,
    "model_output": "Under The Code of Civil Procedure, 1908, Primary Evidence refers to original documents or instruments that were produced by the plaintiff for the court's review. It is distinct from secondary evidence, which involves copies or translations. Therefore, (B) Original documents produced for the court is correct."
  },
  {
    "question_no": "84",
    "question_text": "Secondary Evidence may be given when:",
    "options": {
      "A": "Original is non-transferable",
      "B": "Original is admitted",
      "C": "Original is a public document",
      "D": "Original is in possession of the adversary"
    },
    "correct_answer": "D",
    "correct_text": "D) Possession of adversary",
    "predicted_answer": "A",
    "is_correct": false,
    "model_output": "Under the Indian Evidence Act, 1870, the Supreme Court has ruled that secondary evidence is admissible when the original is non-transferable or destroyed. Therefore, (A) Original is non-transferable is correct."
  },
  {
    "question_no": "85",
    "question_text": "Hostile Witness is provided under section:",
    "options": {
      "A": "152",
      "B": "153",
      "C": "154",
      "D": "155"
    },
    "correct_answer": "C",
    "correct_text": "C) 154",
    "predicted_answer": "B",
    "is_correct": false,
    "model_output": "Under The Code of Criminal Procedure, 1898, Schedule II, Clause (c) defines the provisions for the protection of a hostile witness. Any person who is suspected of being hostile to a person accused in a criminal case and is willing to make false statements is prohibited from testifying. Therefore, (B) 153 is correct."
  },
  {
    "question_no": "86",
    "question_text": "The limitation for a suit for Specific Performance of a contract is:",
    "options": {
      "A": "6 years",
      "B": "3 years",
      "C": "2 years",
      "D": "1 year"
    },
    "correct_answer": "D",
    "correct_text": "D) 1 year",
    "predicted_answer": "C",
    "is_correct": false,
    "model_output": "Under The Limitation Act, 1908, a suit for Specific Performance is filed within two years after the execution of the contract. This short deadline ensures that enforcement of performance remains timely. Therefore, (C) 2 years is correct."
  },
  {
    "question_no": "87",
    "question_text": "Legal Disability is defined in which section of the Limitation Act 1908?",
    "options": {
      "A": "Section 6",
      "B": "Section 8",
      "C": "Section 9",
      "D": "Section 10"
    },
    "correct_answer": "A",
    "correct_text": "A) Section 6",
    "predicted_answer": "B",
    "is_correct": false,
    "model_output": "Under The Limitation Act, 1908, section 8 is known as the Schedule of Disability. It lists the specific types of disabilities that grant a person a right to sue for relief in court. Therefore, (B) Section 8 is correct."
  },
  {
    "question_no": "88",
    "question_text": "Under Section 28, if a suit for recovery of possession is not filed within the specified period, the right to property ________.",
    "options": {
      "A": "Is extinguished",
      "B": "Remains valid",
      "C": "Suspended",
      "D": "Transfers to Govt"
    },
    "correct_answer": "A",
    "correct_text": "A) Extinguished",
    "predicted_answer": "A",
    "is_correct": true,
    "model_output": "Under The Property Recovery Act, 1870, section 28 mandates that a suit for recovery of possession must be filed within thirty days. Failure to file the suit within this period causes the right to the property to be extinguished. Therefore, (A) Is extinguished is correct."
  },
  {
    "question_no": "89",
    "question_text": "Appeal against a death sentence by a Sessions Judge must be filed within 7 days under Article:",
    "options": {
      "A": "148",
      "B": "150",
      "C": "152",
      "D": "154"
    },
    "correct_answer": "B",
    "correct_text": "B) 150",
    "predicted_answer": "C",
    "is_correct": false,
    "model_output": "Under The Code of Criminal Procedure, 1890, Schedule II, Article 152, an appeal against a death sentence must be filed within seven days. Failure to do so results in the conviction being upheld as final. Therefore, (C) 152 is correct."
  },
  {
    "question_no": "90",
    "question_text": "Deadline for applying to set aside an Ex-parte Decree:",
    "options": {
      "A": "15 days",
      "B": "30 days",
      "C": "60 days",
      "D": "90 days"
    },
    "correct_answer": "B",
    "correct_text": "B) 30 days",
    "predicted_answer": "C",
    "is_correct": false,
    "model_output": "Under The Arbitration and Conciliation Act, 1996, a party must file their application for the setting aside of an Ex-parte decree within 60 days. This period is calculated from the date the decree was issued. Therefore, (C) 60 days is correct."
  },
  {
    "question_no": "91",
    "question_text": "Deadline for restoration of an appeal heard ex-parte/dismissed for default:",
    "options": {
      "A": "30 days",
      "B": "60 days",
      "C": "90 days",
      "D": "120 days"
    },
    "correct_answer": "A",
    "correct_text": "A) 30 days",
    "predicted_answer": "B",
    "is_correct": false,
    "model_output": "Under The Code of Criminal Procedure, 1898, Section 35(2), if an appeal or a default judgment is heard ex-parte, the time limit for restoration is 60 days. If the appeal is dismissed due to default, the restoration period is also 60 days. Therefore, (B) 60 days is correct."
  },
  {
    "question_no": "92",
    "question_text": "Limitation for recovery of arrears of rent:",
    "options": {
      "A": "3 years",
      "B": "6 years",
      "C": "10 years",
      "D": "12 years"
    },
    "correct_answer": "A",
    "correct_text": "A) 3 years",
    "predicted_answer": "A",
    "is_correct": true,
    "model_output": "Under The Rent Act, 1908, the period for filing a suit for recovery of arrears of rent is three years. This limitation period starts from the day the rent is due and cannot be extended. Therefore, (A) 3 years is correct."
  },
  {
    "question_no": "93",
    "question_text": "Suit for compensation/damages where no specific term is provided:",
    "options": {
      "A": "1 year",
      "B": "3 years",
      "C": "6 years",
      "D": "12 years"
    },
    "correct_answer": "C",
    "correct_text": "C) 6 years",
    "predicted_answer": "C",
    "is_correct": true,
    "model_output": "Under The Code of Criminal Procedure, 1898, the default time limit for filing a compensation suit is six years. Therefore, (C) 6 years is correct."
  },
  {
    "question_no": "94",
    "question_text": "Exclusion of time in legal proceedings is covered in section:",
    "options": {
      "A": "12",
      "B": "13",
      "C": "14",
      "D": "15"
    },
    "correct_answer": "A",
    "correct_text": "A) 12",
    "predicted_answer": "C",
    "is_correct": false,
    "model_output": "Under The Code of Criminal Procedure, 1898, section 14 specifically states that the court may exclude time in criminal proceedings. Therefore, (C) 14 is correct."
  },
  {
    "question_no": "95",
    "question_text": "Pre-emption (Shufa) is an exception to which section regarding death before right to sue accrues?",
    "options": {
      "A": "Money claims",
      "B": "IP claims",
      "C": "Section 17",
      "D": "Declaration"
    },
    "correct_answer": "C",
    "correct_text": "C) Section 17",
    "predicted_answer": "A",
    "is_correct": false,
    "model_output": "Under The Bankruptcy Code, the doctrine of preemption allows a creditor to sue their deceased beneficiary for money claims if the beneficiary is unable to pay. This prevents the estate from paying out while the person remains alive. Therefore, (A) Money claims is correct."
  },
  {
    "question_no": "96",
    "question_text": "Who can be appointed by the Government as Secretary of the Bar Council?",
    "options": {
      "A": "District Judge only",
      "B": "Additional DJ only",
      "C": "District Judge or Additional DJ",
      "D": "Any judicial officer"
    },
    "correct_answer": "C",
    "correct_text": "C) DJ or Additional DJ",
    "predicted_answer": "C",
    "is_correct": true,
    "model_output": "Under The Bar Council Act, 1967, the Secretary of the Bar Council is appointed by the Government. They can appoint either a District Judge or an Additional District Judge (ADJ) to serve as the head of the council. Therefore, (C) District Judge or Additional DJ is correct."
  },
  {
    "question_no": "97",
    "question_text": "Who has the right of Pre-audience (Right to speak first) in court?",
    "options": {
      "A": "Chief Justice",
      "B": "Bar President",
      "C": "Enrollment Chairman",
      "D": "Attorney General of Bangladesh"
    },
    "correct_answer": "D",
    "correct_text": "D) Attorney General",
    "predicted_answer": "C",
    "is_correct": false,
    "model_output": "Under The Code of Civil Procedure, 1908, section 6, Subsection (1), the right of Pre-audience is granted to anyone who has filed their own case. Therefore, (C) Enrollment Chairman is correct."
  },
  {
    "question_no": "98",
    "question_text": "An Advocate shall not represent conflicting interests. This is a duty towards:",
    "options": {
      "A": "Court",
      "B": "Other Advocates",
      "C": "Public",
      "D": "Client"
    },
    "correct_answer": "B",
    "correct_text": "B) Other Advocates",
    "predicted_answer": "B",
    "is_correct": true,
    "model_output": "Under The Advocates Act, 1961, the Advocate has a fundamental duty to remain impartial and avoid any conflict of interest. This obligation is directed specifically at other advocates who may have conflicting interests with the person they are representing. Therefore, (B) Other Advocates is correct."
  },
  {
    "question_no": "99",
    "question_text": "An Advocate shall not represent conflicting interests. This is also a duty towards:",
    "options": {
      "A": "Court",
      "B": "Other Advocates",
      "C": "Public",
      "D": "The Client"
    },
    "correct_answer": "D",
    "correct_text": "D) The Client",
    "predicted_answer": "D",
    "is_correct": true,
    "model_output": "Under The Advocates Act, 1961, the Advocate has a specific fiduciary duty to avoid conflicts of interest. This is known as the duty of candor and impartiality. When an advocate represents a client, they must remain neutral and free from any other relationships that could impair their judgment or create bias. Therefore, (D) The Client is correct."
  },
  {
    "question_no": "100",
    "question_text": "Which of the following constitutes Professional Misconduct?",
    "options": {
      "A": "Refusal of a brief",
      "B": "Briefing another lawyer",
      "C": "Engaging in another trade or business",
      "D": "Charging fees based on effort"
    },
    "correct_answer": "C",
    "correct_text": "C) Engaging in business",
    "predicted_answer": "A",
    "is_correct": false,
    "model_output": "Under the Code of Professional Conduct, Professional Misconduct occurs when a lawyer fails to follow professional duties. This includes failing to report a client's misconduct, refusing to defend a client in court, or failing to file for their release. Therefore, (A) Refusal of a brief is correct."
  }
]